scinet/__init__.py
scinet/core/__init__.py
scinet/core/graph.py
scinet/utils/__init__.py
scinet/utils/profiler.py
tests/__init__.py
tests/test_graph.py
scinet_josugoar-0.5.5.dist-info/LICENSE
scinet_josugoar-0.5.5.dist-info/METADATA
scinet_josugoar-0.5.5.dist-info/WHEEL
scinet_josugoar-0.5.5.dist-info/top_level.txt
scinet_josugoar-0.5.5.dist-info/RECORD
