Metadata-Version: 2.1
Name: scinet-josugoar
Version: 0.5.5
Summary: Network science abstract data types
Home-page: https://github.com/josugoar/scinet
Author: josugoar
License: UNKNOWN
Download-URL: https://github.com/josugoar/scinet/archive/v0.5.5.tar.gz
Project-URL: Source, https://github.com/josugoar/scinet
Keywords: algorithms data-structures docker graph library pipenv python unittest
Platform: UNKNOWN
Classifier: Programming Language :: Python :: 3
Classifier: License :: OSI Approved :: MIT License
Classifier: Operating System :: OS Independent
Requires-Python: >=3.8
